README.md
setup.cfg
setup.py
xSW01.py
xinabox_SW01.egg-info/PKG-INFO
xinabox_SW01.egg-info/SOURCES.txt
xinabox_SW01.egg-info/dependency_links.txt
xinabox_SW01.egg-info/requires.txt
xinabox_SW01.egg-info/top_level.txt